[{"sequenceLength": 1, "task": "t1", "userid": "01", "dataset": "birdstrikes1"}, {"sequenceLength": 3, "task": "t1", "userid": "01", "dataset": "birdstrikes1"}, {"sequenceLength": 3, "task": "t1", "userid": "01", "dataset": "birdstrikes1"}, {"sequenceLength": 6, "task": "t1", "userid": "05", "dataset": "birdstrikes1"}, {"sequenceLength": 4, "task": "t1", "userid": "05", "dataset": "birdstrikes1"}, {"sequenceLength": 6, "task": "t1", "userid": "05", "dataset": "birdstrikes1"}, {"sequenceLength": 1, "task": "t1", "userid": "05", "dataset": "birdstrikes1"}, {"sequenceLength": 1, "task": "t1", "userid": "05", "dataset": "birdstrikes1"}, {"sequenceLength": 4, "task": "t1", "userid": "09", "dataset": "birdstrikes1"}, {"sequenceLength": 1, "task": "t1", "userid": "09", "dataset": "birdstrikes1"}, {"sequenceLength": 6, "task": "t1", "userid": "09", "dataset": "birdstrikes1"}, {"sequenceLength": 7, "task": "t1", "userid": "09", "dataset": "birdstrikes1"}, {"sequenceLength": 2, "task": "t1", "userid": "109", "dataset": "birdstrikes1"}, {"sequenceLength": 8, "task": "t1", "userid": "109", "dataset": "birdstrikes1"}, {"sequenceLength": 1, "task": "t1", "userid": "109", "dataset": "birdstrikes1"}, {"sequenceLength": 2, "task": "t1", "userid": "13", "dataset": "birdstrikes1"}, {"sequenceLength": 15, "task": "t1", "userid": "13", "dataset": "birdstrikes1"}, {"sequenceLength": 16, "task": "t1", "userid": "25", "dataset": "birdstrikes1"}, {"sequenceLength": 4, "task": "t1", "userid": "25", "dataset": "birdstrikes1"}, {"sequenceLength": 2, "task": "t1", "userid": "25", "dataset": "birdstrikes1"}, {"sequenceLength": 1, "task": "t1", "userid": "25", "dataset": "birdstrikes1"}, {"sequenceLength": 11, "task": "t1", "userid": "25", "dataset": "birdstrikes1"}, {"sequenceLength": 9, "task": "t1", "userid": "33", "dataset": "birdstrikes1"}, {"sequenceLength": 1, "task": "t1", "userid": "33", "dataset": "birdstrikes1"}, {"sequenceLength": 2, "task": "t1", "userid": "33", "dataset": "birdstrikes1"}, {"sequenceLength": 3, "task": "t1", "userid": "37", "dataset": "birdstrikes1"}, {"sequenceLength": 3, "task": "t1", "userid": "37", "dataset": "birdstrikes1"}, {"sequenceLength": 3, "task": "t1", "userid": "53", "dataset": "birdstrikes1"}, {"sequenceLength": 2, "task": "t1", "userid": "53", "dataset": "birdstrikes1"}, {"sequenceLength": 2, "task": "t1", "userid": "53", "dataset": "birdstrikes1"}, {"sequenceLength": 15, "task": "t1", "userid": "53", "dataset": "birdstrikes1"}, {"sequenceLength": 2, "task": "t1", "userid": "57", "dataset": "birdstrikes1"}, {"sequenceLength": 12, "task": "t1", "userid": "57", "dataset": "birdstrikes1"}, {"sequenceLength": 1, "task": "t1", "userid": "61", "dataset": "birdstrikes1"}, {"sequenceLength": 15, "task": "t1", "userid": "61", "dataset": "birdstrikes1"}, {"sequenceLength": 3, "task": "t1", "userid": "61", "dataset": "birdstrikes1"}, {"sequenceLength": 8, "task": "t1", "userid": "61", "dataset": "birdstrikes1"}, {"sequenceLength": 11, "task": "t1", "userid": "61", "dataset": "birdstrikes1"}, {"sequenceLength": 1, "task": "t1", "userid": "61", "dataset": "birdstrikes1"}, {"sequenceLength": 1, "task": "t1", "userid": "61", "dataset": "birdstrikes1"}, {"sequenceLength": 3, "task": "t1", "userid": "61", "dataset": "birdstrikes1"}, {"sequenceLength": 1, "task": "t1", "userid": "61", "dataset": "birdstrikes1"}, {"sequenceLength": 5, "task": "t1", "userid": "73", "dataset": "birdstrikes1"}, {"sequenceLength": 4, "task": "t1", "userid": "73", "dataset": "birdstrikes1"}, {"sequenceLength": 2, "task": "t1", "userid": "73", "dataset": "birdstrikes1"}, {"sequenceLength": 3, "task": "t1", "userid": "77", "dataset": "birdstrikes1"}, {"sequenceLength": 6, "task": "t1", "userid": "77", "dataset": "birdstrikes1"}, {"sequenceLength": 1, "task": "t1", "userid": "77", "dataset": "birdstrikes1"}, {"sequenceLength": 1, "task": "t1", "userid": "81", "dataset": "birdstrikes1"}, {"sequenceLength": 1, "task": "t1", "userid": "81", "dataset": "birdstrikes1"}, {"sequenceLength": 5, "task": "t1", "userid": "81", "dataset": "birdstrikes1"}, {"sequenceLength": 1, "task": "t1", "userid": "81", "dataset": "birdstrikes1"}, {"sequenceLength": 1, "task": "t1", "userid": "81", "dataset": "birdstrikes1"}, {"sequenceLength": 1, "task": "t1", "userid": "97", "dataset": "birdstrikes1"}, {"sequenceLength": 1, "task": "t1", "userid": "97", "dataset": "birdstrikes1"}, {"sequenceLength": 2, "task": "t2", "userid": "01", "dataset": "birdstrikes1"}, {"sequenceLength": 1, "task": "t2", "userid": "05", "dataset": "birdstrikes1"}, {"sequenceLength": 1, "task": "t2", "userid": "05", "dataset": "birdstrikes1"}, {"sequenceLength": 3, "task": "t2", "userid": "05", "dataset": "birdstrikes1"}, {"sequenceLength": 5, "task": "t2", "userid": "09", "dataset": "birdstrikes1"}, {"sequenceLength": 3, "task": "t2", "userid": "09", "dataset": "birdstrikes1"}, {"sequenceLength": 1, "task": "t2", "userid": "09", "dataset": "birdstrikes1"}, {"sequenceLength": 4, "task": "t2", "userid": "09", "dataset": "birdstrikes1"}, {"sequenceLength": 2, "task": "t2", "userid": "109", "dataset": "birdstrikes1"}, {"sequenceLength": 2, "task": "t2", "userid": "109", "dataset": "birdstrikes1"}, {"sequenceLength": 1, "task": "t2", "userid": "109", "dataset": "birdstrikes1"}, {"sequenceLength": 3, "task": "t2", "userid": "109", "dataset": "birdstrikes1"}, {"sequenceLength": 1, "task": "t2", "userid": "109", "dataset": "birdstrikes1"}, {"sequenceLength": 1, "task": "t2", "userid": "13", "dataset": "birdstrikes1"}, {"sequenceLength": 3, "task": "t2", "userid": "13", "dataset": "birdstrikes1"}, {"sequenceLength": 2, "task": "t2", "userid": "13", "dataset": "birdstrikes1"}, {"sequenceLength": 1, "task": "t2", "userid": "13", "dataset": "birdstrikes1"}, {"sequenceLength": 5, "task": "t2", "userid": "25", "dataset": "birdstrikes1"}, {"sequenceLength": 2, "task": "t2", "userid": "25", "dataset": "birdstrikes1"}, {"sequenceLength": 6, "task": "t2", "userid": "29", "dataset": "birdstrikes1"}, {"sequenceLength": 1, "task": "t2", "userid": "29", "dataset": "birdstrikes1"}, {"sequenceLength": 2, "task": "t2", "userid": "29", "dataset": "birdstrikes1"}, {"sequenceLength": 1, "task": "t2", "userid": "33", "dataset": "birdstrikes1"}, {"sequenceLength": 5, "task": "t2", "userid": "33", "dataset": "birdstrikes1"}, {"sequenceLength": 12, "task": "t2", "userid": "33", "dataset": "birdstrikes1"}, {"sequenceLength": 5, "task": "t2", "userid": "33", "dataset": "birdstrikes1"}, {"sequenceLength": 5, "task": "t2", "userid": "37", "dataset": "birdstrikes1"}, {"sequenceLength": 1, "task": "t2", "userid": "37", "dataset": "birdstrikes1"}, {"sequenceLength": 2, "task": "t2", "userid": "37", "dataset": "birdstrikes1"}, {"sequenceLength": 2, "task": "t2", "userid": "37", "dataset": "birdstrikes1"}, {"sequenceLength": 6, "task": "t2", "userid": "53", "dataset": "birdstrikes1"}, {"sequenceLength": 1, "task": "t2", "userid": "53", "dataset": "birdstrikes1"}, {"sequenceLength": 1, "task": "t2", "userid": "53", "dataset": "birdstrikes1"}, {"sequenceLength": 3, "task": "t2", "userid": "57", "dataset": "birdstrikes1"}, {"sequenceLength": 3, "task": "t2", "userid": "57", "dataset": "birdstrikes1"}, {"sequenceLength": 2, "task": "t2", "userid": "57", "dataset": "birdstrikes1"}, {"sequenceLength": 5, "task": "t2", "userid": "57", "dataset": "birdstrikes1"}, {"sequenceLength": 2, "task": "t2", "userid": "57", "dataset": "birdstrikes1"}, {"sequenceLength": 6, "task": "t2", "userid": "61", "dataset": "birdstrikes1"}, {"sequenceLength": 7, "task": "t2", "userid": "73", "dataset": "birdstrikes1"}, {"sequenceLength": 2, "task": "t2", "userid": "73", "dataset": "birdstrikes1"}, {"sequenceLength": 2, "task": "t2", "userid": "73", "dataset": "birdstrikes1"}, {"sequenceLength": 2, "task": "t2", "userid": "73", "dataset": "birdstrikes1"}, {"sequenceLength": 5, "task": "t2", "userid": "73", "dataset": "birdstrikes1"}, {"sequenceLength": 10, "task": "t2", "userid": "73", "dataset": "birdstrikes1"}, {"sequenceLength": 2, "task": "t2", "userid": "73", "dataset": "birdstrikes1"}, {"sequenceLength": 5, "task": "t2", "userid": "73", "dataset": "birdstrikes1"}, {"sequenceLength": 1, "task": "t2", "userid": "77", "dataset": "birdstrikes1"}, {"sequenceLength": 5, "task": "t2", "userid": "77", "dataset": "birdstrikes1"}, {"sequenceLength": 5, "task": "t2", "userid": "77", "dataset": "birdstrikes1"}, {"sequenceLength": 2, "task": "t2", "userid": "77", "dataset": "birdstrikes1"}, {"sequenceLength": 1, "task": "t2", "userid": "81", "dataset": "birdstrikes1"}, {"sequenceLength": 3, "task": "t2", "userid": "81", "dataset": "birdstrikes1"}, {"sequenceLength": 5, "task": "t2", "userid": "81", "dataset": "birdstrikes1"}, {"sequenceLength": 2, "task": "t2", "userid": "97", "dataset": "birdstrikes1"}, {"sequenceLength": 7, "task": "t2", "userid": "97", "dataset": "birdstrikes1"}, {"sequenceLength": 3, "task": "t2", "userid": "97", "dataset": "birdstrikes1"}, {"sequenceLength": 4, "task": "t2", "userid": "97", "dataset": "birdstrikes1"}, {"sequenceLength": 7, "task": "t2", "userid": "97", "dataset": "birdstrikes1"}, {"sequenceLength": 5, "task": "t2", "userid": "97", "dataset": "birdstrikes1"}, {"sequenceLength": 2, "task": "t3", "userid": "01", "dataset": "birdstrikes1"}, {"sequenceLength": 1, "task": "t3", "userid": "05", "dataset": "birdstrikes1"}, {"sequenceLength": 4, "task": "t3", "userid": "05", "dataset": "birdstrikes1"}, {"sequenceLength": 1, "task": "t3", "userid": "05", "dataset": "birdstrikes1"}, {"sequenceLength": 8, "task": "t3", "userid": "05", "dataset": "birdstrikes1"}, {"sequenceLength": 2, "task": "t3", "userid": "05", "dataset": "birdstrikes1"}, {"sequenceLength": 2, "task": "t3", "userid": "05", "dataset": "birdstrikes1"}, {"sequenceLength": 2, "task": "t3", "userid": "09", "dataset": "birdstrikes1"}, {"sequenceLength": 1, "task": "t3", "userid": "09", "dataset": "birdstrikes1"}, {"sequenceLength": 1, "task": "t3", "userid": "09", "dataset": "birdstrikes1"}, {"sequenceLength": 3, "task": "t3", "userid": "09", "dataset": "birdstrikes1"}, {"sequenceLength": 7, "task": "t3", "userid": "09", "dataset": "birdstrikes1"}, {"sequenceLength": 1, "task": "t3", "userid": "109", "dataset": "birdstrikes1"}, {"sequenceLength": 1, "task": "t3", "userid": "109", "dataset": "birdstrikes1"}, {"sequenceLength": 1, "task": "t3", "userid": "109", "dataset": "birdstrikes1"}, {"sequenceLength": 2, "task": "t3", "userid": "109", "dataset": "birdstrikes1"}, {"sequenceLength": 5, "task": "t3", "userid": "109", "dataset": "birdstrikes1"}, {"sequenceLength": 21, "task": "t3", "userid": "109", "dataset": "birdstrikes1"}, {"sequenceLength": 1, "task": "t3", "userid": "13", "dataset": "birdstrikes1"}, {"sequenceLength": 1, "task": "t3", "userid": "13", "dataset": "birdstrikes1"}, {"sequenceLength": 2, "task": "t3", "userid": "13", "dataset": "birdstrikes1"}, {"sequenceLength": 1, "task": "t3", "userid": "13", "dataset": "birdstrikes1"}, {"sequenceLength": 1, "task": "t3", "userid": "13", "dataset": "birdstrikes1"}, {"sequenceLength": 4, "task": "t3", "userid": "13", "dataset": "birdstrikes1"}, {"sequenceLength": 2, "task": "t3", "userid": "13", "dataset": "birdstrikes1"}, {"sequenceLength": 1, "task": "t3", "userid": "25", "dataset": "birdstrikes1"}, {"sequenceLength": 5, "task": "t3", "userid": "25", "dataset": "birdstrikes1"}, {"sequenceLength": 9, "task": "t3", "userid": "25", "dataset": "birdstrikes1"}, {"sequenceLength": 4, "task": "t3", "userid": "29", "dataset": "birdstrikes1"}, {"sequenceLength": 1, "task": "t3", "userid": "29", "dataset": "birdstrikes1"}, {"sequenceLength": 4, "task": "t3", "userid": "29", "dataset": "birdstrikes1"}, {"sequenceLength": 9, "task": "t3", "userid": "33", "dataset": "birdstrikes1"}, {"sequenceLength": 1, "task": "t3", "userid": "33", "dataset": "birdstrikes1"}, {"sequenceLength": 7, "task": "t3", "userid": "33", "dataset": "birdstrikes1"}, {"sequenceLength": 1, "task": "t3", "userid": "33", "dataset": "birdstrikes1"}, {"sequenceLength": 12, "task": "t3", "userid": "33", "dataset": "birdstrikes1"}, {"sequenceLength": 4, "task": "t3", "userid": "37", "dataset": "birdstrikes1"}, {"sequenceLength": 1, "task": "t3", "userid": "37", "dataset": "birdstrikes1"}, {"sequenceLength": 1, "task": "t3", "userid": "37", "dataset": "birdstrikes1"}, {"sequenceLength": 2, "task": "t3", "userid": "53", "dataset": "birdstrikes1"}, {"sequenceLength": 1, "task": "t3", "userid": "53", "dataset": "birdstrikes1"}, {"sequenceLength": 1, "task": "t3", "userid": "53", "dataset": "birdstrikes1"}, {"sequenceLength": 1, "task": "t3", "userid": "53", "dataset": "birdstrikes1"}, {"sequenceLength": 1, "task": "t3", "userid": "53", "dataset": "birdstrikes1"}, {"sequenceLength": 3, "task": "t3", "userid": "57", "dataset": "birdstrikes1"}, {"sequenceLength": 1, "task": "t3", "userid": "57", "dataset": "birdstrikes1"}, {"sequenceLength": 3, "task": "t3", "userid": "57", "dataset": "birdstrikes1"}, {"sequenceLength": 1, "task": "t3", "userid": "61", "dataset": "birdstrikes1"}, {"sequenceLength": 1, "task": "t3", "userid": "61", "dataset": "birdstrikes1"}, {"sequenceLength": 2, "task": "t3", "userid": "61", "dataset": "birdstrikes1"}, {"sequenceLength": 4, "task": "t3", "userid": "61", "dataset": "birdstrikes1"}, {"sequenceLength": 7, "task": "t3", "userid": "61", "dataset": "birdstrikes1"}, {"sequenceLength": 5, "task": "t3", "userid": "61", "dataset": "birdstrikes1"}, {"sequenceLength": 4, "task": "t3", "userid": "73", "dataset": "birdstrikes1"}, {"sequenceLength": 4, "task": "t3", "userid": "73", "dataset": "birdstrikes1"}, {"sequenceLength": 3, "task": "t3", "userid": "73", "dataset": "birdstrikes1"}, {"sequenceLength": 2, "task": "t3", "userid": "73", "dataset": "birdstrikes1"}, {"sequenceLength": 5, "task": "t3", "userid": "77", "dataset": "birdstrikes1"}, {"sequenceLength": 1, "task": "t3", "userid": "77", "dataset": "birdstrikes1"}, {"sequenceLength": 8, "task": "t3", "userid": "77", "dataset": "birdstrikes1"}, {"sequenceLength": 2, "task": "t3", "userid": "77", "dataset": "birdstrikes1"}, {"sequenceLength": 6, "task": "t3", "userid": "77", "dataset": "birdstrikes1"}, {"sequenceLength": 8, "task": "t3", "userid": "77", "dataset": "birdstrikes1"}, {"sequenceLength": 2, "task": "t3", "userid": "81", "dataset": "birdstrikes1"}, {"sequenceLength": 2, "task": "t3", "userid": "81", "dataset": "birdstrikes1"}, {"sequenceLength": 1, "task": "t3", "userid": "81", "dataset": "birdstrikes1"}, {"sequenceLength": 3, "task": "t3", "userid": "85", "dataset": "birdstrikes1"}, {"sequenceLength": 2, "task": "t3", "userid": "85", "dataset": "birdstrikes1"}, {"sequenceLength": 7, "task": "t3", "userid": "97", "dataset": "birdstrikes1"}, {"sequenceLength": 3, "task": "t3", "userid": "97", "dataset": "birdstrikes1"}, {"sequenceLength": 8, "task": "t3", "userid": "97", "dataset": "birdstrikes1"}, {"sequenceLength": 4, "task": "t4", "userid": "01", "dataset": "birdstrikes1"}, {"sequenceLength": 1, "task": "t4", "userid": "01", "dataset": "birdstrikes1"}, {"sequenceLength": 3, "task": "t4", "userid": "01", "dataset": "birdstrikes1"}, {"sequenceLength": 2, "task": "t4", "userid": "01", "dataset": "birdstrikes1"}, {"sequenceLength": 2, "task": "t4", "userid": "01", "dataset": "birdstrikes1"}, {"sequenceLength": 3, "task": "t4", "userid": "01", "dataset": "birdstrikes1"}, {"sequenceLength": 1, "task": "t4", "userid": "01", "dataset": "birdstrikes1"}, {"sequenceLength": 5, "task": "t4", "userid": "05", "dataset": "birdstrikes1"}, {"sequenceLength": 8, "task": "t4", "userid": "05", "dataset": "birdstrikes1"}, {"sequenceLength": 5, "task": "t4", "userid": "05", "dataset": "birdstrikes1"}, {"sequenceLength": 5, "task": "t4", "userid": "05", "dataset": "birdstrikes1"}, {"sequenceLength": 4, "task": "t4", "userid": "05", "dataset": "birdstrikes1"}, {"sequenceLength": 1, "task": "t4", "userid": "05", "dataset": "birdstrikes1"}, {"sequenceLength": 3, "task": "t4", "userid": "09", "dataset": "birdstrikes1"}, {"sequenceLength": 6, "task": "t4", "userid": "09", "dataset": "birdstrikes1"}, {"sequenceLength": 6, "task": "t4", "userid": "09", "dataset": "birdstrikes1"}, {"sequenceLength": 4, "task": "t4", "userid": "09", "dataset": "birdstrikes1"}, {"sequenceLength": 8, "task": "t4", "userid": "09", "dataset": "birdstrikes1"}, {"sequenceLength": 3, "task": "t4", "userid": "109", "dataset": "birdstrikes1"}, {"sequenceLength": 1, "task": "t4", "userid": "109", "dataset": "birdstrikes1"}, {"sequenceLength": 1, "task": "t4", "userid": "109", "dataset": "birdstrikes1"}, {"sequenceLength": 5, "task": "t4", "userid": "109", "dataset": "birdstrikes1"}, {"sequenceLength": 1, "task": "t4", "userid": "109", "dataset": "birdstrikes1"}, {"sequenceLength": 3, "task": "t4", "userid": "109", "dataset": "birdstrikes1"}, {"sequenceLength": 1, "task": "t4", "userid": "13", "dataset": "birdstrikes1"}, {"sequenceLength": 4, "task": "t4", "userid": "13", "dataset": "birdstrikes1"}, {"sequenceLength": 1, "task": "t4", "userid": "13", "dataset": "birdstrikes1"}, {"sequenceLength": 4, "task": "t4", "userid": "13", "dataset": "birdstrikes1"}, {"sequenceLength": 1, "task": "t4", "userid": "13", "dataset": "birdstrikes1"}, {"sequenceLength": 4, "task": "t4", "userid": "25", "dataset": "birdstrikes1"}, {"sequenceLength": 15, "task": "t4", "userid": "25", "dataset": "birdstrikes1"}, {"sequenceLength": 1, "task": "t4", "userid": "25", "dataset": "birdstrikes1"}, {"sequenceLength": 3, "task": "t4", "userid": "25", "dataset": "birdstrikes1"}, {"sequenceLength": 4, "task": "t4", "userid": "25", "dataset": "birdstrikes1"}, {"sequenceLength": 2, "task": "t4", "userid": "25", "dataset": "birdstrikes1"}, {"sequenceLength": 1, "task": "t4", "userid": "25", "dataset": "birdstrikes1"}, {"sequenceLength": 1, "task": "t4", "userid": "29", "dataset": "birdstrikes1"}, {"sequenceLength": 1, "task": "t4", "userid": "29", "dataset": "birdstrikes1"}, {"sequenceLength": 2, "task": "t4", "userid": "29", "dataset": "birdstrikes1"}, {"sequenceLength": 2, "task": "t4", "userid": "29", "dataset": "birdstrikes1"}, {"sequenceLength": 2, "task": "t4", "userid": "29", "dataset": "birdstrikes1"}, {"sequenceLength": 2, "task": "t4", "userid": "29", "dataset": "birdstrikes1"}, {"sequenceLength": 4, "task": "t4", "userid": "29", "dataset": "birdstrikes1"}, {"sequenceLength": 1, "task": "t4", "userid": "29", "dataset": "birdstrikes1"}, {"sequenceLength": 9, "task": "t4", "userid": "33", "dataset": "birdstrikes1"}, {"sequenceLength": 1, "task": "t4", "userid": "33", "dataset": "birdstrikes1"}, {"sequenceLength": 2, "task": "t4", "userid": "33", "dataset": "birdstrikes1"}, {"sequenceLength": 10, "task": "t4", "userid": "33", "dataset": "birdstrikes1"}, {"sequenceLength": 2, "task": "t4", "userid": "33", "dataset": "birdstrikes1"}, {"sequenceLength": 5, "task": "t4", "userid": "33", "dataset": "birdstrikes1"}, {"sequenceLength": 6, "task": "t4", "userid": "33", "dataset": "birdstrikes1"}, {"sequenceLength": 1, "task": "t4", "userid": "37", "dataset": "birdstrikes1"}, {"sequenceLength": 3, "task": "t4", "userid": "37", "dataset": "birdstrikes1"}, {"sequenceLength": 8, "task": "t4", "userid": "37", "dataset": "birdstrikes1"}, {"sequenceLength": 5, "task": "t4", "userid": "37", "dataset": "birdstrikes1"}, {"sequenceLength": 8, "task": "t4", "userid": "37", "dataset": "birdstrikes1"}, {"sequenceLength": 1, "task": "t4", "userid": "37", "dataset": "birdstrikes1"}, {"sequenceLength": 6, "task": "t4", "userid": "37", "dataset": "birdstrikes1"}, {"sequenceLength": 1, "task": "t4", "userid": "53", "dataset": "birdstrikes1"}, {"sequenceLength": 1, "task": "t4", "userid": "53", "dataset": "birdstrikes1"}, {"sequenceLength": 1, "task": "t4", "userid": "53", "dataset": "birdstrikes1"}, {"sequenceLength": 1, "task": "t4", "userid": "53", "dataset": "birdstrikes1"}, {"sequenceLength": 1, "task": "t4", "userid": "53", "dataset": "birdstrikes1"}, {"sequenceLength": 4, "task": "t4", "userid": "53", "dataset": "birdstrikes1"}, {"sequenceLength": 1, "task": "t4", "userid": "53", "dataset": "birdstrikes1"}, {"sequenceLength": 1, "task": "t4", "userid": "53", "dataset": "birdstrikes1"}, {"sequenceLength": 1, "task": "t4", "userid": "57", "dataset": "birdstrikes1"}, {"sequenceLength": 5, "task": "t4", "userid": "57", "dataset": "birdstrikes1"}, {"sequenceLength": 2, "task": "t4", "userid": "57", "dataset": "birdstrikes1"}, {"sequenceLength": 1, "task": "t4", "userid": "57", "dataset": "birdstrikes1"}, {"sequenceLength": 1, "task": "t4", "userid": "57", "dataset": "birdstrikes1"}, {"sequenceLength": 1, "task": "t4", "userid": "57", "dataset": "birdstrikes1"}, {"sequenceLength": 6, "task": "t4", "userid": "57", "dataset": "birdstrikes1"}, {"sequenceLength": 3, "task": "t4", "userid": "57", "dataset": "birdstrikes1"}, {"sequenceLength": 2, "task": "t4", "userid": "61", "dataset": "birdstrikes1"}, {"sequenceLength": 3, "task": "t4", "userid": "61", "dataset": "birdstrikes1"}, {"sequenceLength": 5, "task": "t4", "userid": "61", "dataset": "birdstrikes1"}, {"sequenceLength": 3, "task": "t4", "userid": "73", "dataset": "birdstrikes1"}, {"sequenceLength": 3, "task": "t4", "userid": "73", "dataset": "birdstrikes1"}, {"sequenceLength": 1, "task": "t4", "userid": "73", "dataset": "birdstrikes1"}, {"sequenceLength": 1, "task": "t4", "userid": "73", "dataset": "birdstrikes1"}, {"sequenceLength": 5, "task": "t4", "userid": "73", "dataset": "birdstrikes1"}, {"sequenceLength": 7, "task": "t4", "userid": "73", "dataset": "birdstrikes1"}, {"sequenceLength": 4, "task": "t4", "userid": "73", "dataset": "birdstrikes1"}, {"sequenceLength": 1, "task": "t4", "userid": "77", "dataset": "birdstrikes1"}, {"sequenceLength": 6, "task": "t4", "userid": "77", "dataset": "birdstrikes1"}, {"sequenceLength": 7, "task": "t4", "userid": "77", "dataset": "birdstrikes1"}, {"sequenceLength": 12, "task": "t4", "userid": "77", "dataset": "birdstrikes1"}, {"sequenceLength": 2, "task": "t4", "userid": "77", "dataset": "birdstrikes1"}, {"sequenceLength": 1, "task": "t4", "userid": "77", "dataset": "birdstrikes1"}, {"sequenceLength": 1, "task": "t4", "userid": "77", "dataset": "birdstrikes1"}, {"sequenceLength": 1, "task": "t4", "userid": "77", "dataset": "birdstrikes1"}, {"sequenceLength": 2, "task": "t4", "userid": "81", "dataset": "birdstrikes1"}, {"sequenceLength": 2, "task": "t4", "userid": "81", "dataset": "birdstrikes1"}, {"sequenceLength": 2, "task": "t4", "userid": "81", "dataset": "birdstrikes1"}, {"sequenceLength": 1, "task": "t4", "userid": "81", "dataset": "birdstrikes1"}, {"sequenceLength": 3, "task": "t4", "userid": "81", "dataset": "birdstrikes1"}, {"sequenceLength": 1, "task": "t4", "userid": "85", "dataset": "birdstrikes1"}, {"sequenceLength": 2, "task": "t4", "userid": "85", "dataset": "birdstrikes1"}, {"sequenceLength": 1, "task": "t4", "userid": "85", "dataset": "birdstrikes1"}, {"sequenceLength": 10, "task": "t4", "userid": "85", "dataset": "birdstrikes1"}, {"sequenceLength": 10, "task": "t4", "userid": "85", "dataset": "birdstrikes1"}, {"sequenceLength": 1, "task": "t4", "userid": "97", "dataset": "birdstrikes1"}, {"sequenceLength": 4, "task": "t4", "userid": "97", "dataset": "birdstrikes1"}, {"sequenceLength": 1, "task": "t4", "userid": "97", "dataset": "birdstrikes1"}, {"sequenceLength": 2, "task": "t4", "userid": "97", "dataset": "birdstrikes1"}, {"sequenceLength": 2, "task": "t4", "userid": "97", "dataset": "birdstrikes1"}, {"sequenceLength": 3, "task": "t4", "userid": "97", "dataset": "birdstrikes1"}, {"sequenceLength": 2, "task": "t4", "userid": "97", "dataset": "birdstrikes1"}, {"sequenceLength": 1, "task": "t1", "userid": "09", "dataset": "faa1"}, {"sequenceLength": 10, "task": "t1", "userid": "09", "dataset": "faa1"}, {"sequenceLength": 4, "task": "t1", "userid": "09", "dataset": "faa1"}, {"sequenceLength": 4, "task": "t1", "userid": "109", "dataset": "faa1"}, {"sequenceLength": 12, "task": "t1", "userid": "109", "dataset": "faa1"}, {"sequenceLength": 1, "task": "t1", "userid": "109", "dataset": "faa1"}, {"sequenceLength": 2, "task": "t1", "userid": "13", "dataset": "faa1"}, {"sequenceLength": 4, "task": "t1", "userid": "13", "dataset": "faa1"}, {"sequenceLength": 1, "task": "t1", "userid": "13", "dataset": "faa1"}, {"sequenceLength": 3, "task": "t1", "userid": "21", "dataset": "faa1"}, {"sequenceLength": 2, "task": "t1", "userid": "21", "dataset": "faa1"}, {"sequenceLength": 3, "task": "t1", "userid": "21", "dataset": "faa1"}, {"sequenceLength": 1, "task": "t1", "userid": "33", "dataset": "faa1"}, {"sequenceLength": 3, "task": "t1", "userid": "33", "dataset": "faa1"}, {"sequenceLength": 4, "task": "t1", "userid": "33", "dataset": "faa1"}, {"sequenceLength": 8, "task": "t1", "userid": "33", "dataset": "faa1"}, {"sequenceLength": 4, "task": "t1", "userid": "37", "dataset": "faa1"}, {"sequenceLength": 5, "task": "t1", "userid": "37", "dataset": "faa1"}, {"sequenceLength": 1, "task": "t1", "userid": "37", "dataset": "faa1"}, {"sequenceLength": 4, "task": "t1", "userid": "37", "dataset": "faa1"}, {"sequenceLength": 3, "task": "t1", "userid": "37", "dataset": "faa1"}, {"sequenceLength": 1, "task": "t1", "userid": "41", "dataset": "faa1"}, {"sequenceLength": 7, "task": "t1", "userid": "41", "dataset": "faa1"}, {"sequenceLength": 1, "task": "t1", "userid": "41", "dataset": "faa1"}, {"sequenceLength": 3, "task": "t1", "userid": "41", "dataset": "faa1"}, {"sequenceLength": 10, "task": "t1", "userid": "45", "dataset": "faa1"}, {"sequenceLength": 2, "task": "t1", "userid": "45", "dataset": "faa1"}, {"sequenceLength": 3, "task": "t1", "userid": "57", "dataset": "faa1"}, {"sequenceLength": 1, "task": "t1", "userid": "57", "dataset": "faa1"}, {"sequenceLength": 4, "task": "t1", "userid": "57", "dataset": "faa1"}, {"sequenceLength": 6, "task": "t1", "userid": "57", "dataset": "faa1"}, {"sequenceLength": 8, "task": "t1", "userid": "65", "dataset": "faa1"}, {"sequenceLength": 2, "task": "t1", "userid": "65", "dataset": "faa1"}, {"sequenceLength": 1, "task": "t1", "userid": "65", "dataset": "faa1"}, {"sequenceLength": 1, "task": "t1", "userid": "65", "dataset": "faa1"}, {"sequenceLength": 3, "task": "t1", "userid": "65", "dataset": "faa1"}, {"sequenceLength": 5, "task": "t1", "userid": "69", "dataset": "faa1"}, {"sequenceLength": 4, "task": "t1", "userid": "69", "dataset": "faa1"}, {"sequenceLength": 2, "task": "t1", "userid": "69", "dataset": "faa1"}, {"sequenceLength": 3, "task": "t1", "userid": "69", "dataset": "faa1"}, {"sequenceLength": 4, "task": "t1", "userid": "69", "dataset": "faa1"}, {"sequenceLength": 1, "task": "t1", "userid": "69", "dataset": "faa1"}, {"sequenceLength": 4, "task": "t1", "userid": "81", "dataset": "faa1"}, {"sequenceLength": 1, "task": "t1", "userid": "81", "dataset": "faa1"}, {"sequenceLength": 3, "task": "t1", "userid": "81", "dataset": "faa1"}, {"sequenceLength": 1, "task": "t1", "userid": "81", "dataset": "faa1"}, {"sequenceLength": 1, "task": "t1", "userid": "81", "dataset": "faa1"}, {"sequenceLength": 1, "task": "t1", "userid": "81", "dataset": "faa1"}, {"sequenceLength": 1, "task": "t1", "userid": "85", "dataset": "faa1"}, {"sequenceLength": 9, "task": "t1", "userid": "89", "dataset": "faa1"}, {"sequenceLength": 5, "task": "t1", "userid": "89", "dataset": "faa1"}, {"sequenceLength": 1, "task": "t1", "userid": "89", "dataset": "faa1"}, {"sequenceLength": 1, "task": "t1", "userid": "89", "dataset": "faa1"}, {"sequenceLength": 4, "task": "t1", "userid": "89", "dataset": "faa1"}, {"sequenceLength": 8, "task": "t1", "userid": "93", "dataset": "faa1"}, {"sequenceLength": 1, "task": "t1", "userid": "93", "dataset": "faa1"}, {"sequenceLength": 11, "task": "t1", "userid": "93", "dataset": "faa1"}, {"sequenceLength": 1, "task": "t1", "userid": "93", "dataset": "faa1"}, {"sequenceLength": 1, "task": "t2", "userid": "09", "dataset": "faa1"}, {"sequenceLength": 1, "task": "t2", "userid": "09", "dataset": "faa1"}, {"sequenceLength": 5, "task": "t2", "userid": "09", "dataset": "faa1"}, {"sequenceLength": 18, "task": "t2", "userid": "09", "dataset": "faa1"}, {"sequenceLength": 2, "task": "t2", "userid": "109", "dataset": "faa1"}, {"sequenceLength": 4, "task": "t2", "userid": "109", "dataset": "faa1"}, {"sequenceLength": 2, "task": "t2", "userid": "109", "dataset": "faa1"}, {"sequenceLength": 2, "task": "t2", "userid": "13", "dataset": "faa1"}, {"sequenceLength": 3, "task": "t2", "userid": "13", "dataset": "faa1"}, {"sequenceLength": 13, "task": "t2", "userid": "21", "dataset": "faa1"}, {"sequenceLength": 10, "task": "t2", "userid": "21", "dataset": "faa1"}, {"sequenceLength": 2, "task": "t2", "userid": "21", "dataset": "faa1"}, {"sequenceLength": 5, "task": "t2", "userid": "33", "dataset": "faa1"}, {"sequenceLength": 2, "task": "t2", "userid": "33", "dataset": "faa1"}, {"sequenceLength": 10, "task": "t2", "userid": "33", "dataset": "faa1"}, {"sequenceLength": 2, "task": "t2", "userid": "37", "dataset": "faa1"}, {"sequenceLength": 3, "task": "t2", "userid": "37", "dataset": "faa1"}, {"sequenceLength": 2, "task": "t2", "userid": "37", "dataset": "faa1"}, {"sequenceLength": 1, "task": "t2", "userid": "41", "dataset": "faa1"}, {"sequenceLength": 1, "task": "t2", "userid": "41", "dataset": "faa1"}, {"sequenceLength": 2, "task": "t2", "userid": "41", "dataset": "faa1"}, {"sequenceLength": 2, "task": "t2", "userid": "41", "dataset": "faa1"}, {"sequenceLength": 8, "task": "t2", "userid": "45", "dataset": "faa1"}, {"sequenceLength": 6, "task": "t2", "userid": "45", "dataset": "faa1"}, {"sequenceLength": 1, "task": "t2", "userid": "57", "dataset": "faa1"}, {"sequenceLength": 2, "task": "t2", "userid": "57", "dataset": "faa1"}, {"sequenceLength": 2, "task": "t2", "userid": "57", "dataset": "faa1"}, {"sequenceLength": 2, "task": "t2", "userid": "57", "dataset": "faa1"}, {"sequenceLength": 1, "task": "t2", "userid": "57", "dataset": "faa1"}, {"sequenceLength": 1, "task": "t2", "userid": "57", "dataset": "faa1"}, {"sequenceLength": 1, "task": "t2", "userid": "65", "dataset": "faa1"}, {"sequenceLength": 1, "task": "t2", "userid": "65", "dataset": "faa1"}, {"sequenceLength": 2, "task": "t2", "userid": "69", "dataset": "faa1"}, {"sequenceLength": 19, "task": "t2", "userid": "69", "dataset": "faa1"}, {"sequenceLength": 5, "task": "t2", "userid": "69", "dataset": "faa1"}, {"sequenceLength": 3, "task": "t2", "userid": "69", "dataset": "faa1"}, {"sequenceLength": 2, "task": "t2", "userid": "81", "dataset": "faa1"}, {"sequenceLength": 1, "task": "t2", "userid": "85", "dataset": "faa1"}, {"sequenceLength": 2, "task": "t2", "userid": "85", "dataset": "faa1"}, {"sequenceLength": 1, "task": "t2", "userid": "85", "dataset": "faa1"}, {"sequenceLength": 1, "task": "t2", "userid": "89", "dataset": "faa1"}, {"sequenceLength": 2, "task": "t2", "userid": "89", "dataset": "faa1"}, {"sequenceLength": 2, "task": "t2", "userid": "93", "dataset": "faa1"}, {"sequenceLength": 4, "task": "t2", "userid": "93", "dataset": "faa1"}, {"sequenceLength": 9, "task": "t2", "userid": "93", "dataset": "faa1"}, {"sequenceLength": 5, "task": "t3", "userid": "09", "dataset": "faa1"}, {"sequenceLength": 1, "task": "t3", "userid": "09", "dataset": "faa1"}, {"sequenceLength": 1, "task": "t3", "userid": "109", "dataset": "faa1"}, {"sequenceLength": 3, "task": "t3", "userid": "109", "dataset": "faa1"}, {"sequenceLength": 5, "task": "t3", "userid": "109", "dataset": "faa1"}, {"sequenceLength": 8, "task": "t3", "userid": "109", "dataset": "faa1"}, {"sequenceLength": 1, "task": "t3", "userid": "13", "dataset": "faa1"}, {"sequenceLength": 2, "task": "t3", "userid": "13", "dataset": "faa1"}, {"sequenceLength": 1, "task": "t3", "userid": "21", "dataset": "faa1"}, {"sequenceLength": 2, "task": "t3", "userid": "21", "dataset": "faa1"}, {"sequenceLength": 2, "task": "t3", "userid": "21", "dataset": "faa1"}, {"sequenceLength": 4, "task": "t3", "userid": "33", "dataset": "faa1"}, {"sequenceLength": 2, "task": "t3", "userid": "33", "dataset": "faa1"}, {"sequenceLength": 7, "task": "t3", "userid": "37", "dataset": "faa1"}, {"sequenceLength": 1, "task": "t3", "userid": "37", "dataset": "faa1"}, {"sequenceLength": 2, "task": "t3", "userid": "37", "dataset": "faa1"}, {"sequenceLength": 8, "task": "t3", "userid": "37", "dataset": "faa1"}, {"sequenceLength": 2, "task": "t3", "userid": "41", "dataset": "faa1"}, {"sequenceLength": 1, "task": "t3", "userid": "41", "dataset": "faa1"}, {"sequenceLength": 1, "task": "t3", "userid": "41", "dataset": "faa1"}, {"sequenceLength": 3, "task": "t3", "userid": "41", "dataset": "faa1"}, {"sequenceLength": 2, "task": "t3", "userid": "45", "dataset": "faa1"}, {"sequenceLength": 1, "task": "t3", "userid": "45", "dataset": "faa1"}, {"sequenceLength": 2, "task": "t3", "userid": "57", "dataset": "faa1"}, {"sequenceLength": 1, "task": "t3", "userid": "57", "dataset": "faa1"}, {"sequenceLength": 3, "task": "t3", "userid": "57", "dataset": "faa1"}, {"sequenceLength": 3, "task": "t3", "userid": "57", "dataset": "faa1"}, {"sequenceLength": 4, "task": "t3", "userid": "65", "dataset": "faa1"}, {"sequenceLength": 6, "task": "t3", "userid": "69", "dataset": "faa1"}, {"sequenceLength": 3, "task": "t3", "userid": "69", "dataset": "faa1"}, {"sequenceLength": 2, "task": "t3", "userid": "69", "dataset": "faa1"}, {"sequenceLength": 3, "task": "t3", "userid": "69", "dataset": "faa1"}, {"sequenceLength": 2, "task": "t3", "userid": "69", "dataset": "faa1"}, {"sequenceLength": 9, "task": "t3", "userid": "69", "dataset": "faa1"}, {"sequenceLength": 2, "task": "t3", "userid": "69", "dataset": "faa1"}, {"sequenceLength": 3, "task": "t3", "userid": "81", "dataset": "faa1"}, {"sequenceLength": 4, "task": "t3", "userid": "81", "dataset": "faa1"}, {"sequenceLength": 5, "task": "t3", "userid": "81", "dataset": "faa1"}, {"sequenceLength": 1, "task": "t3", "userid": "81", "dataset": "faa1"}, {"sequenceLength": 3, "task": "t3", "userid": "81", "dataset": "faa1"}, {"sequenceLength": 2, "task": "t3", "userid": "85", "dataset": "faa1"}, {"sequenceLength": 5, "task": "t3", "userid": "85", "dataset": "faa1"}, {"sequenceLength": 5, "task": "t3", "userid": "85", "dataset": "faa1"}, {"sequenceLength": 1, "task": "t3", "userid": "85", "dataset": "faa1"}, {"sequenceLength": 4, "task": "t3", "userid": "89", "dataset": "faa1"}, {"sequenceLength": 1, "task": "t3", "userid": "89", "dataset": "faa1"}, {"sequenceLength": 1, "task": "t3", "userid": "89", "dataset": "faa1"}, {"sequenceLength": 2, "task": "t3", "userid": "89", "dataset": "faa1"}, {"sequenceLength": 1, "task": "t3", "userid": "89", "dataset": "faa1"}, {"sequenceLength": 7, "task": "t3", "userid": "93", "dataset": "faa1"}, {"sequenceLength": 1, "task": "t3", "userid": "93", "dataset": "faa1"}, {"sequenceLength": 8, "task": "t4", "userid": "09", "dataset": "faa1"}, {"sequenceLength": 4, "task": "t4", "userid": "09", "dataset": "faa1"}, {"sequenceLength": 1, "task": "t4", "userid": "09", "dataset": "faa1"}, {"sequenceLength": 7, "task": "t4", "userid": "09", "dataset": "faa1"}, {"sequenceLength": 3, "task": "t4", "userid": "09", "dataset": "faa1"}, {"sequenceLength": 3, "task": "t4", "userid": "09", "dataset": "faa1"}, {"sequenceLength": 4, "task": "t4", "userid": "09", "dataset": "faa1"}, {"sequenceLength": 3, "task": "t4", "userid": "109", "dataset": "faa1"}, {"sequenceLength": 7, "task": "t4", "userid": "109", "dataset": "faa1"}, {"sequenceLength": 1, "task": "t4", "userid": "109", "dataset": "faa1"}, {"sequenceLength": 4, "task": "t4", "userid": "109", "dataset": "faa1"}, {"sequenceLength": 4, "task": "t4", "userid": "109", "dataset": "faa1"}, {"sequenceLength": 3, "task": "t4", "userid": "109", "dataset": "faa1"}, {"sequenceLength": 4, "task": "t4", "userid": "13", "dataset": "faa1"}, {"sequenceLength": 5, "task": "t4", "userid": "13", "dataset": "faa1"}, {"sequenceLength": 1, "task": "t4", "userid": "13", "dataset": "faa1"}, {"sequenceLength": 1, "task": "t4", "userid": "21", "dataset": "faa1"}, {"sequenceLength": 2, "task": "t4", "userid": "21", "dataset": "faa1"}, {"sequenceLength": 6, "task": "t4", "userid": "21", "dataset": "faa1"}, {"sequenceLength": 15, "task": "t4", "userid": "21", "dataset": "faa1"}, {"sequenceLength": 5, "task": "t4", "userid": "21", "dataset": "faa1"}, {"sequenceLength": 1, "task": "t4", "userid": "33", "dataset": "faa1"}, {"sequenceLength": 8, "task": "t4", "userid": "33", "dataset": "faa1"}, {"sequenceLength": 7, "task": "t4", "userid": "33", "dataset": "faa1"}, {"sequenceLength": 3, "task": "t4", "userid": "33", "dataset": "faa1"}, {"sequenceLength": 5, "task": "t4", "userid": "33", "dataset": "faa1"}, {"sequenceLength": 18, "task": "t4", "userid": "37", "dataset": "faa1"}, {"sequenceLength": 4, "task": "t4", "userid": "37", "dataset": "faa1"}, {"sequenceLength": 3, "task": "t4", "userid": "37", "dataset": "faa1"}, {"sequenceLength": 11, "task": "t4", "userid": "37", "dataset": "faa1"}, {"sequenceLength": 1, "task": "t4", "userid": "41", "dataset": "faa1"}, {"sequenceLength": 1, "task": "t4", "userid": "41", "dataset": "faa1"}, {"sequenceLength": 1, "task": "t4", "userid": "41", "dataset": "faa1"}, {"sequenceLength": 1, "task": "t4", "userid": "41", "dataset": "faa1"}, {"sequenceLength": 3, "task": "t4", "userid": "45", "dataset": "faa1"}, {"sequenceLength": 1, "task": "t4", "userid": "45", "dataset": "faa1"}, {"sequenceLength": 4, "task": "t4", "userid": "57", "dataset": "faa1"}, {"sequenceLength": 1, "task": "t4", "userid": "57", "dataset": "faa1"}, {"sequenceLength": 1, "task": "t4", "userid": "57", "dataset": "faa1"}, {"sequenceLength": 3, "task": "t4", "userid": "57", "dataset": "faa1"}, {"sequenceLength": 9, "task": "t4", "userid": "57", "dataset": "faa1"}, {"sequenceLength": 6, "task": "t4", "userid": "57", "dataset": "faa1"}, {"sequenceLength": 4, "task": "t4", "userid": "65", "dataset": "faa1"}, {"sequenceLength": 2, "task": "t4", "userid": "69", "dataset": "faa1"}, {"sequenceLength": 3, "task": "t4", "userid": "69", "dataset": "faa1"}, {"sequenceLength": 8, "task": "t4", "userid": "69", "dataset": "faa1"}, {"sequenceLength": 9, "task": "t4", "userid": "69", "dataset": "faa1"}, {"sequenceLength": 9, "task": "t4", "userid": "69", "dataset": "faa1"}, {"sequenceLength": 3, "task": "t4", "userid": "69", "dataset": "faa1"}, {"sequenceLength": 2, "task": "t4", "userid": "81", "dataset": "faa1"}, {"sequenceLength": 8, "task": "t4", "userid": "81", "dataset": "faa1"}, {"sequenceLength": 1, "task": "t4", "userid": "81", "dataset": "faa1"}, {"sequenceLength": 2, "task": "t4", "userid": "81", "dataset": "faa1"}, {"sequenceLength": 6, "task": "t4", "userid": "81", "dataset": "faa1"}, {"sequenceLength": 4, "task": "t4", "userid": "85", "dataset": "faa1"}, {"sequenceLength": 1, "task": "t4", "userid": "89", "dataset": "faa1"}, {"sequenceLength": 1, "task": "t4", "userid": "89", "dataset": "faa1"}, {"sequenceLength": 1, "task": "t4", "userid": "89", "dataset": "faa1"}, {"sequenceLength": 4, "task": "t4", "userid": "89", "dataset": "faa1"}, {"sequenceLength": 5, "task": "t4", "userid": "89", "dataset": "faa1"}, {"sequenceLength": 4, "task": "t4", "userid": "89", "dataset": "faa1"}, {"sequenceLength": 2, "task": "t4", "userid": "89", "dataset": "faa1"}, {"sequenceLength": 3, "task": "t4", "userid": "89", "dataset": "faa1"}, {"sequenceLength": 6, "task": "t4", "userid": "89", "dataset": "faa1"}, {"sequenceLength": 7, "task": "t4", "userid": "93", "dataset": "faa1"}, {"sequenceLength": 3, "task": "t4", "userid": "93", "dataset": "faa1"}, {"sequenceLength": 3, "task": "t4", "userid": "93", "dataset": "faa1"}, {"sequenceLength": 3, "task": "t4", "userid": "93", "dataset": "faa1"}, {"sequenceLength": 2, "task": "t4", "userid": "93", "dataset": "faa1"}, {"sequenceLength": 1, "task": "t4", "userid": "93", "dataset": "faa1"}, {"sequenceLength": 1, "task": "t1", "userid": "01", "dataset": "weather1"}, {"sequenceLength": 4, "task": "t1", "userid": "01", "dataset": "weather1"}, {"sequenceLength": 3, "task": "t1", "userid": "01", "dataset": "weather1"}, {"sequenceLength": 2, "task": "t1", "userid": "01", "dataset": "weather1"}, {"sequenceLength": 9, "task": "t1", "userid": "05", "dataset": "weather1"}, {"sequenceLength": 15, "task": "t1", "userid": "05", "dataset": "weather1"}, {"sequenceLength": 2, "task": "t1", "userid": "05", "dataset": "weather1"}, {"sequenceLength": 1, "task": "t1", "userid": "05", "dataset": "weather1"}, {"sequenceLength": 3, "task": "t1", "userid": "05", "dataset": "weather1"}, {"sequenceLength": 3, "task": "t1", "userid": "113", "dataset": "weather1"}, {"sequenceLength": 5, "task": "t1", "userid": "113", "dataset": "weather1"}, {"sequenceLength": 5, "task": "t1", "userid": "117", "dataset": "weather1"}, {"sequenceLength": 3, "task": "t1", "userid": "117", "dataset": "weather1"}, {"sequenceLength": 2, "task": "t1", "userid": "117", "dataset": "weather1"}, {"sequenceLength": 3, "task": "t1", "userid": "117", "dataset": "weather1"}, {"sequenceLength": 6, "task": "t1", "userid": "117", "dataset": "weather1"}, {"sequenceLength": 7, "task": "t1", "userid": "21", "dataset": "weather1"}, {"sequenceLength": 1, "task": "t1", "userid": "21", "dataset": "weather1"}, {"sequenceLength": 11, "task": "t1", "userid": "25", "dataset": "weather1"}, {"sequenceLength": 1, "task": "t1", "userid": "29", "dataset": "weather1"}, {"sequenceLength": 5, "task": "t1", "userid": "41", "dataset": "weather1"}, {"sequenceLength": 2, "task": "t1", "userid": "41", "dataset": "weather1"}, {"sequenceLength": 1, "task": "t1", "userid": "41", "dataset": "weather1"}, {"sequenceLength": 4, "task": "t1", "userid": "41", "dataset": "weather1"}, {"sequenceLength": 4, "task": "t1", "userid": "41", "dataset": "weather1"}, {"sequenceLength": 3, "task": "t1", "userid": "41", "dataset": "weather1"}, {"sequenceLength": 1, "task": "t1", "userid": "45", "dataset": "weather1"}, {"sequenceLength": 4, "task": "t1", "userid": "45", "dataset": "weather1"}, {"sequenceLength": 4, "task": "t1", "userid": "45", "dataset": "weather1"}, {"sequenceLength": 7, "task": "t1", "userid": "53", "dataset": "weather1"}, {"sequenceLength": 22, "task": "t1", "userid": "53", "dataset": "weather1"}, {"sequenceLength": 2, "task": "t1", "userid": "65", "dataset": "weather1"}, {"sequenceLength": 4, "task": "t1", "userid": "65", "dataset": "weather1"}, {"sequenceLength": 8, "task": "t1", "userid": "69", "dataset": "weather1"}, {"sequenceLength": 4, "task": "t1", "userid": "69", "dataset": "weather1"}, {"sequenceLength": 1, "task": "t1", "userid": "69", "dataset": "weather1"}, {"sequenceLength": 1, "task": "t1", "userid": "69", "dataset": "weather1"}, {"sequenceLength": 7, "task": "t1", "userid": "73", "dataset": "weather1"}, {"sequenceLength": 2, "task": "t1", "userid": "73", "dataset": "weather1"}, {"sequenceLength": 3, "task": "t1", "userid": "73", "dataset": "weather1"}, {"sequenceLength": 9, "task": "t1", "userid": "93", "dataset": "weather1"}, {"sequenceLength": 1, "task": "t1", "userid": "93", "dataset": "weather1"}, {"sequenceLength": 1, "task": "t1", "userid": "93", "dataset": "weather1"}, {"sequenceLength": 4, "task": "t1", "userid": "97", "dataset": "weather1"}, {"sequenceLength": 2, "task": "t1", "userid": "97", "dataset": "weather1"}, {"sequenceLength": 11, "task": "t2", "userid": "01", "dataset": "weather1"}, {"sequenceLength": 6, "task": "t2", "userid": "01", "dataset": "weather1"}, {"sequenceLength": 1, "task": "t2", "userid": "01", "dataset": "weather1"}, {"sequenceLength": 9, "task": "t2", "userid": "05", "dataset": "weather1"}, {"sequenceLength": 2, "task": "t2", "userid": "05", "dataset": "weather1"}, {"sequenceLength": 10, "task": "t2", "userid": "05", "dataset": "weather1"}, {"sequenceLength": 1, "task": "t2", "userid": "05", "dataset": "weather1"}, {"sequenceLength": 2, "task": "t2", "userid": "113", "dataset": "weather1"}, {"sequenceLength": 1, "task": "t2", "userid": "113", "dataset": "weather1"}, {"sequenceLength": 2, "task": "t2", "userid": "113", "dataset": "weather1"}, {"sequenceLength": 4, "task": "t2", "userid": "113", "dataset": "weather1"}, {"sequenceLength": 3, "task": "t2", "userid": "113", "dataset": "weather1"}, {"sequenceLength": 1, "task": "t2", "userid": "113", "dataset": "weather1"}, {"sequenceLength": 6, "task": "t2", "userid": "117", "dataset": "weather1"}, {"sequenceLength": 2, "task": "t2", "userid": "117", "dataset": "weather1"}, {"sequenceLength": 1, "task": "t2", "userid": "117", "dataset": "weather1"}, {"sequenceLength": 4, "task": "t2", "userid": "117", "dataset": "weather1"}, {"sequenceLength": 2, "task": "t2", "userid": "21", "dataset": "weather1"}, {"sequenceLength": 6, "task": "t2", "userid": "21", "dataset": "weather1"}, {"sequenceLength": 2, "task": "t2", "userid": "21", "dataset": "weather1"}, {"sequenceLength": 1, "task": "t2", "userid": "21", "dataset": "weather1"}, {"sequenceLength": 1, "task": "t2", "userid": "25", "dataset": "weather1"}, {"sequenceLength": 2, "task": "t2", "userid": "25", "dataset": "weather1"}, {"sequenceLength": 3, "task": "t2", "userid": "29", "dataset": "weather1"}, {"sequenceLength": 3, "task": "t2", "userid": "29", "dataset": "weather1"}, {"sequenceLength": 1, "task": "t2", "userid": "41", "dataset": "weather1"}, {"sequenceLength": 1, "task": "t2", "userid": "41", "dataset": "weather1"}, {"sequenceLength": 6, "task": "t2", "userid": "41", "dataset": "weather1"}, {"sequenceLength": 6, "task": "t2", "userid": "41", "dataset": "weather1"}, {"sequenceLength": 3, "task": "t2", "userid": "45", "dataset": "weather1"}, {"sequenceLength": 1, "task": "t2", "userid": "45", "dataset": "weather1"}, {"sequenceLength": 9, "task": "t2", "userid": "53", "dataset": "weather1"}, {"sequenceLength": 7, "task": "t2", "userid": "53", "dataset": "weather1"}, {"sequenceLength": 5, "task": "t2", "userid": "53", "dataset": "weather1"}, {"sequenceLength": 1, "task": "t2", "userid": "53", "dataset": "weather1"}, {"sequenceLength": 4, "task": "t2", "userid": "65", "dataset": "weather1"}, {"sequenceLength": 2, "task": "t2", "userid": "69", "dataset": "weather1"}, {"sequenceLength": 1, "task": "t2", "userid": "69", "dataset": "weather1"}, {"sequenceLength": 4, "task": "t2", "userid": "69", "dataset": "weather1"}, {"sequenceLength": 3, "task": "t2", "userid": "69", "dataset": "weather1"}, {"sequenceLength": 1, "task": "t2", "userid": "69", "dataset": "weather1"}, {"sequenceLength": 2, "task": "t2", "userid": "69", "dataset": "weather1"}, {"sequenceLength": 2, "task": "t2", "userid": "69", "dataset": "weather1"}, {"sequenceLength": 5, "task": "t2", "userid": "73", "dataset": "weather1"}, {"sequenceLength": 4, "task": "t2", "userid": "73", "dataset": "weather1"}, {"sequenceLength": 1, "task": "t2", "userid": "73", "dataset": "weather1"}, {"sequenceLength": 1, "task": "t2", "userid": "73", "dataset": "weather1"}, {"sequenceLength": 1, "task": "t2", "userid": "73", "dataset": "weather1"}, {"sequenceLength": 6, "task": "t2", "userid": "73", "dataset": "weather1"}, {"sequenceLength": 1, "task": "t2", "userid": "77", "dataset": "weather1"}, {"sequenceLength": 3, "task": "t2", "userid": "77", "dataset": "weather1"}, {"sequenceLength": 2, "task": "t2", "userid": "77", "dataset": "weather1"}, {"sequenceLength": 5, "task": "t2", "userid": "77", "dataset": "weather1"}, {"sequenceLength": 3, "task": "t2", "userid": "93", "dataset": "weather1"}, {"sequenceLength": 1, "task": "t2", "userid": "93", "dataset": "weather1"}, {"sequenceLength": 1, "task": "t2", "userid": "93", "dataset": "weather1"}, {"sequenceLength": 3, "task": "t2", "userid": "93", "dataset": "weather1"}, {"sequenceLength": 2, "task": "t2", "userid": "93", "dataset": "weather1"}, {"sequenceLength": 1, "task": "t2", "userid": "97", "dataset": "weather1"}, {"sequenceLength": 4, "task": "t2", "userid": "97", "dataset": "weather1"}, {"sequenceLength": 1, "task": "t2", "userid": "97", "dataset": "weather1"}, {"sequenceLength": 1, "task": "t2", "userid": "97", "dataset": "weather1"}, {"sequenceLength": 1, "task": "t2", "userid": "97", "dataset": "weather1"}, {"sequenceLength": 1, "task": "t2", "userid": "97", "dataset": "weather1"}, {"sequenceLength": 4, "task": "t3", "userid": "01", "dataset": "weather1"}, {"sequenceLength": 4, "task": "t3", "userid": "01", "dataset": "weather1"}, {"sequenceLength": 4, "task": "t3", "userid": "05", "dataset": "weather1"}, {"sequenceLength": 6, "task": "t3", "userid": "05", "dataset": "weather1"}, {"sequenceLength": 1, "task": "t3", "userid": "05", "dataset": "weather1"}, {"sequenceLength": 4, "task": "t3", "userid": "113", "dataset": "weather1"}, {"sequenceLength": 8, "task": "t3", "userid": "113", "dataset": "weather1"}, {"sequenceLength": 7, "task": "t3", "userid": "113", "dataset": "weather1"}, {"sequenceLength": 6, "task": "t3", "userid": "117", "dataset": "weather1"}, {"sequenceLength": 1, "task": "t3", "userid": "117", "dataset": "weather1"}, {"sequenceLength": 1, "task": "t3", "userid": "117", "dataset": "weather1"}, {"sequenceLength": 7, "task": "t3", "userid": "117", "dataset": "weather1"}, {"sequenceLength": 2, "task": "t3", "userid": "117", "dataset": "weather1"}, {"sequenceLength": 3, "task": "t3", "userid": "117", "dataset": "weather1"}, {"sequenceLength": 1, "task": "t3", "userid": "21", "dataset": "weather1"}, {"sequenceLength": 2, "task": "t3", "userid": "25", "dataset": "weather1"}, {"sequenceLength": 5, "task": "t3", "userid": "25", "dataset": "weather1"}, {"sequenceLength": 3, "task": "t3", "userid": "25", "dataset": "weather1"}, {"sequenceLength": 9, "task": "t3", "userid": "29", "dataset": "weather1"}, {"sequenceLength": 7, "task": "t3", "userid": "29", "dataset": "weather1"}, {"sequenceLength": 2, "task": "t3", "userid": "29", "dataset": "weather1"}, {"sequenceLength": 8, "task": "t3", "userid": "41", "dataset": "weather1"}, {"sequenceLength": 4, "task": "t3", "userid": "41", "dataset": "weather1"}, {"sequenceLength": 2, "task": "t3", "userid": "45", "dataset": "weather1"}, {"sequenceLength": 5, "task": "t3", "userid": "53", "dataset": "weather1"}, {"sequenceLength": 9, "task": "t3", "userid": "53", "dataset": "weather1"}, {"sequenceLength": 5, "task": "t3", "userid": "53", "dataset": "weather1"}, {"sequenceLength": 2, "task": "t3", "userid": "65", "dataset": "weather1"}, {"sequenceLength": 6, "task": "t3", "userid": "69", "dataset": "weather1"}, {"sequenceLength": 1, "task": "t3", "userid": "69", "dataset": "weather1"}, {"sequenceLength": 7, "task": "t3", "userid": "69", "dataset": "weather1"}, {"sequenceLength": 4, "task": "t3", "userid": "73", "dataset": "weather1"}, {"sequenceLength": 4, "task": "t3", "userid": "73", "dataset": "weather1"}, {"sequenceLength": 1, "task": "t3", "userid": "73", "dataset": "weather1"}, {"sequenceLength": 2, "task": "t3", "userid": "73", "dataset": "weather1"}, {"sequenceLength": 1, "task": "t3", "userid": "73", "dataset": "weather1"}, {"sequenceLength": 6, "task": "t3", "userid": "77", "dataset": "weather1"}, {"sequenceLength": 7, "task": "t3", "userid": "77", "dataset": "weather1"}, {"sequenceLength": 1, "task": "t3", "userid": "77", "dataset": "weather1"}, {"sequenceLength": 1, "task": "t3", "userid": "93", "dataset": "weather1"}, {"sequenceLength": 1, "task": "t3", "userid": "93", "dataset": "weather1"}, {"sequenceLength": 2, "task": "t3", "userid": "93", "dataset": "weather1"}, {"sequenceLength": 6, "task": "t3", "userid": "93", "dataset": "weather1"}, {"sequenceLength": 2, "task": "t3", "userid": "97", "dataset": "weather1"}, {"sequenceLength": 2, "task": "t3", "userid": "97", "dataset": "weather1"}, {"sequenceLength": 9, "task": "t3", "userid": "97", "dataset": "weather1"}, {"sequenceLength": 10, "task": "t3", "userid": "97", "dataset": "weather1"}, {"sequenceLength": 2, "task": "t3", "userid": "97", "dataset": "weather1"}, {"sequenceLength": 1, "task": "t4", "userid": "01", "dataset": "weather1"}, {"sequenceLength": 8, "task": "t4", "userid": "01", "dataset": "weather1"}, {"sequenceLength": 5, "task": "t4", "userid": "01", "dataset": "weather1"}, {"sequenceLength": 2, "task": "t4", "userid": "01", "dataset": "weather1"}, {"sequenceLength": 3, "task": "t4", "userid": "01", "dataset": "weather1"}, {"sequenceLength": 3, "task": "t4", "userid": "01", "dataset": "weather1"}, {"sequenceLength": 2, "task": "t4", "userid": "01", "dataset": "weather1"}, {"sequenceLength": 2, "task": "t4", "userid": "01", "dataset": "weather1"}, {"sequenceLength": 4, "task": "t4", "userid": "01", "dataset": "weather1"}, {"sequenceLength": 4, "task": "t4", "userid": "01", "dataset": "weather1"}, {"sequenceLength": 12, "task": "t4", "userid": "05", "dataset": "weather1"}, {"sequenceLength": 4, "task": "t4", "userid": "05", "dataset": "weather1"}, {"sequenceLength": 4, "task": "t4", "userid": "05", "dataset": "weather1"}, {"sequenceLength": 4, "task": "t4", "userid": "05", "dataset": "weather1"}, {"sequenceLength": 2, "task": "t4", "userid": "05", "dataset": "weather1"}, {"sequenceLength": 1, "task": "t4", "userid": "05", "dataset": "weather1"}, {"sequenceLength": 1, "task": "t4", "userid": "113", "dataset": "weather1"}, {"sequenceLength": 3, "task": "t4", "userid": "113", "dataset": "weather1"}, {"sequenceLength": 1, "task": "t4", "userid": "113", "dataset": "weather1"}, {"sequenceLength": 1, "task": "t4", "userid": "113", "dataset": "weather1"}, {"sequenceLength": 3, "task": "t4", "userid": "113", "dataset": "weather1"}, {"sequenceLength": 1, "task": "t4", "userid": "113", "dataset": "weather1"}, {"sequenceLength": 2, "task": "t4", "userid": "117", "dataset": "weather1"}, {"sequenceLength": 1, "task": "t4", "userid": "117", "dataset": "weather1"}, {"sequenceLength": 8, "task": "t4", "userid": "117", "dataset": "weather1"}, {"sequenceLength": 1, "task": "t4", "userid": "117", "dataset": "weather1"}, {"sequenceLength": 3, "task": "t4", "userid": "117", "dataset": "weather1"}, {"sequenceLength": 3, "task": "t4", "userid": "21", "dataset": "weather1"}, {"sequenceLength": 6, "task": "t4", "userid": "21", "dataset": "weather1"}, {"sequenceLength": 17, "task": "t4", "userid": "21", "dataset": "weather1"}, {"sequenceLength": 10, "task": "t4", "userid": "21", "dataset": "weather1"}, {"sequenceLength": 1, "task": "t4", "userid": "25", "dataset": "weather1"}, {"sequenceLength": 12, "task": "t4", "userid": "25", "dataset": "weather1"}, {"sequenceLength": 1, "task": "t4", "userid": "25", "dataset": "weather1"}, {"sequenceLength": 4, "task": "t4", "userid": "25", "dataset": "weather1"}, {"sequenceLength": 2, "task": "t4", "userid": "25", "dataset": "weather1"}, {"sequenceLength": 1, "task": "t4", "userid": "25", "dataset": "weather1"}, {"sequenceLength": 2, "task": "t4", "userid": "25", "dataset": "weather1"}, {"sequenceLength": 5, "task": "t4", "userid": "29", "dataset": "weather1"}, {"sequenceLength": 5, "task": "t4", "userid": "29", "dataset": "weather1"}, {"sequenceLength": 1, "task": "t4", "userid": "29", "dataset": "weather1"}, {"sequenceLength": 1, "task": "t4", "userid": "29", "dataset": "weather1"}, {"sequenceLength": 1, "task": "t4", "userid": "29", "dataset": "weather1"}, {"sequenceLength": 4, "task": "t4", "userid": "29", "dataset": "weather1"}, {"sequenceLength": 17, "task": "t4", "userid": "41", "dataset": "weather1"}, {"sequenceLength": 9, "task": "t4", "userid": "41", "dataset": "weather1"}, {"sequenceLength": 9, "task": "t4", "userid": "41", "dataset": "weather1"}, {"sequenceLength": 1, "task": "t4", "userid": "45", "dataset": "weather1"}, {"sequenceLength": 3, "task": "t4", "userid": "45", "dataset": "weather1"}, {"sequenceLength": 3, "task": "t4", "userid": "45", "dataset": "weather1"}, {"sequenceLength": 3, "task": "t4", "userid": "45", "dataset": "weather1"}, {"sequenceLength": 5, "task": "t4", "userid": "45", "dataset": "weather1"}, {"sequenceLength": 7, "task": "t4", "userid": "45", "dataset": "weather1"}, {"sequenceLength": 1, "task": "t4", "userid": "45", "dataset": "weather1"}, {"sequenceLength": 3, "task": "t4", "userid": "45", "dataset": "weather1"}, {"sequenceLength": 1, "task": "t4", "userid": "45", "dataset": "weather1"}, {"sequenceLength": 1, "task": "t4", "userid": "45", "dataset": "weather1"}, {"sequenceLength": 1, "task": "t4", "userid": "53", "dataset": "weather1"}, {"sequenceLength": 12, "task": "t4", "userid": "53", "dataset": "weather1"}, {"sequenceLength": 1, "task": "t4", "userid": "53", "dataset": "weather1"}, {"sequenceLength": 1, "task": "t4", "userid": "53", "dataset": "weather1"}, {"sequenceLength": 4, "task": "t4", "userid": "53", "dataset": "weather1"}, {"sequenceLength": 5, "task": "t4", "userid": "53", "dataset": "weather1"}, {"sequenceLength": 2, "task": "t4", "userid": "53", "dataset": "weather1"}, {"sequenceLength": 1, "task": "t4", "userid": "53", "dataset": "weather1"}, {"sequenceLength": 2, "task": "t4", "userid": "65", "dataset": "weather1"}, {"sequenceLength": 1, "task": "t4", "userid": "65", "dataset": "weather1"}, {"sequenceLength": 1, "task": "t4", "userid": "65", "dataset": "weather1"}, {"sequenceLength": 2, "task": "t4", "userid": "65", "dataset": "weather1"}, {"sequenceLength": 3, "task": "t4", "userid": "65", "dataset": "weather1"}, {"sequenceLength": 4, "task": "t4", "userid": "65", "dataset": "weather1"}, {"sequenceLength": 2, "task": "t4", "userid": "65", "dataset": "weather1"}, {"sequenceLength": 4, "task": "t4", "userid": "69", "dataset": "weather1"}, {"sequenceLength": 12, "task": "t4", "userid": "69", "dataset": "weather1"}, {"sequenceLength": 19, "task": "t4", "userid": "69", "dataset": "weather1"}, {"sequenceLength": 2, "task": "t4", "userid": "73", "dataset": "weather1"}, {"sequenceLength": 4, "task": "t4", "userid": "73", "dataset": "weather1"}, {"sequenceLength": 4, "task": "t4", "userid": "73", "dataset": "weather1"}, {"sequenceLength": 11, "task": "t4", "userid": "73", "dataset": "weather1"}, {"sequenceLength": 1, "task": "t4", "userid": "73", "dataset": "weather1"}, {"sequenceLength": 3, "task": "t4", "userid": "77", "dataset": "weather1"}, {"sequenceLength": 1, "task": "t4", "userid": "77", "dataset": "weather1"}, {"sequenceLength": 3, "task": "t4", "userid": "77", "dataset": "weather1"}, {"sequenceLength": 4, "task": "t4", "userid": "93", "dataset": "weather1"}, {"sequenceLength": 2, "task": "t4", "userid": "93", "dataset": "weather1"}, {"sequenceLength": 9, "task": "t4", "userid": "93", "dataset": "weather1"}, {"sequenceLength": 1, "task": "t4", "userid": "93", "dataset": "weather1"}, {"sequenceLength": 3, "task": "t4", "userid": "97", "dataset": "weather1"}, {"sequenceLength": 1, "task": "t4", "userid": "97", "dataset": "weather1"}, {"sequenceLength": 5, "task": "t4", "userid": "97", "dataset": "weather1"}, {"sequenceLength": 4, "task": "t4", "userid": "97", "dataset": "weather1"}, {"sequenceLength": 7, "task": "t4", "userid": "97", "dataset": "weather1"}, {"sequenceLength": 1, "task": "t4", "userid": "97", "dataset": "weather1"}]